DIYables_MicroPython_Servo/DIYables_MicroPython_Servo.py
DIYables_MicroPython_Servo/__init__.py
DIYables_MicroPython_Servo-0.1.0.dist-info/LICENSE
DIYables_MicroPython_Servo-0.1.0.dist-info/METADATA
DIYables_MicroPython_Servo-0.1.0.dist-info/WHEEL
DIYables_MicroPython_Servo-0.1.0.dist-info/top_level.txt
DIYables_MicroPython_Servo-0.1.0.dist-info/RECORD
